vizeer/Sample.mkv
vizeer/__init__.py
vizeer/cli.py
vizeer/core.py
vizeer/scene.py
vizeer/types.py
vizeer/utils.py
vizeer/yy.png
vizeer-0.1.0.dist-info/METADATA
vizeer-0.1.0.dist-info/WHEEL
vizeer-0.1.0.dist-info/entry_points.txt
vizeer-0.1.0.dist-info/RECORD
