Metadata-Version: 2.1
Name: vizeer
Version: 0.1.0
Summary: A video contact sheet generator
Author: walidsa3d
Requires-Python: >=3.10,<4.0
Classifier: Programming Language :: Python :: 3
Classifier: Programming Language :: Python :: 3.10
Classifier: Programming Language :: Python :: 3.11
Classifier: Programming Language :: Python :: 3.12
Classifier: Programming Language :: Python :: 3.13
Requires-Dist: click (>=8.1.3,<9.0.0)
Requires-Dist: moviepy (>=2.1.1,<3.0.0)
Requires-Dist: numpy (>=2.1.3,<3.0.0)
Requires-Dist: opencv-python (>=4.10.0.84,<5.0.0.0)
Requires-Dist: pymediainfo (>=6.1.0,<7.0.0)
Requires-Dist: scenedetect[opencv] (>=0.6.5,<0.7.0)
